GradTree/GradTree.py
GradTree/__init__.py
GradTree-0.1.0.dist-info/LICENSE
GradTree-0.1.0.dist-info/METADATA
GradTree-0.1.0.dist-info/WHEEL
GradTree-0.1.0.dist-info/top_level.txt
GradTree-0.1.0.dist-info/RECORD
