Metadata-Version: 2.1
Name: GradTree
Version: 0.1.0
Summary: A novel method for learning hard, axis-aligned decision trees with gradient descent.
Home-page: https://github.com/s-marton/GradTree
Author: Sascha Marton
Author-email: sascha.marton@gmail.com
License-File: LICENSE
Requires-Dist: focal-loss >=0.0.7
Requires-Dist: category-encoders >=2.6.1
Requires-Dist: pandas >=2.0.3
Requires-Dist: tensorflow-addons >=0.21.0
Requires-Dist: tensorflow ==2.13
Requires-Dist: numpy >=1.23.2
Requires-Dist: scikit-learn >=1.3.0
